{"namedChunkGroups":{"polyfill":{"name":"polyfill","assets":[{"name":"webpack-runtime-9ed5c2b54c8d6b6c0139.js","size":3136},{"name":"polyfill-4d4aae668e7c0282a75c.js","size":82493}],"filteredAssets":0,"assetsSize":85629,"filteredAuxiliaryAssets":2,"auxiliaryAssetsSize":214031},"app":{"name":"app","assets":[{"name":"webpack-runtime-9ed5c2b54c8d6b6c0139.js","size":3136},{"name":"framework-f9875ebd8c423ae9906e.js","size":129125},{"name":"app-0602fa687a4d2f1f41da.js","size":50426}],"filteredAssets":0,"assetsSize":182687,"filteredAuxiliaryAssets":3,"auxiliaryAssetsSize":541903},"component---src-pages-404-js":{"name":"component---src-pages-404-js","assets":[{"name":"component---src-pages-404-js-f91e86cfe65092e3adc1.js","size":810}],"filteredAssets":0,"assetsSize":810,"filteredAuxiliaryAssets":1,"auxiliaryAssetsSize":1994},"component---src-pages-index-js":{"name":"component---src-pages-index-js","assets":[{"name":"component---src-pages-index-js-a95b8d386e9a51cae64a.js","size":81637}],"filteredAssets":0,"assetsSize":81637,"filteredAuxiliaryAssets":1,"auxiliaryAssetsSize":380408}},"assetsByChunkName":{"polyfill":["webpack-runtime-9ed5c2b54c8d6b6c0139.js","polyfill-4d4aae668e7c0282a75c.js"],"app":["webpack-runtime-9ed5c2b54c8d6b6c0139.js","framework-f9875ebd8c423ae9906e.js","app-0602fa687a4d2f1f41da.js"],"component---src-pages-404-js":["component---src-pages-404-js-f91e86cfe65092e3adc1.js"],"component---src-pages-index-js":["component---src-pages-index-js-a95b8d386e9a51cae64a.js"]},"childAssetsByChunkName":{}}